{"narrative":{"title":"New Narrative","slides":[{"title":"TOPIC=\"Henri Poincaré\"","text":"Réseau WOS bipartite de \"Authors\" (en bleu) liés à \"Index Keywords\" (en rouge)","snapshot":"7925147e-931f-4356-bd64-5f4f893b6620"}],"space":"57d22325-fc65-47b3-8e42-7f893a489fe0","version":0,"type":"narrative"},"meta":{"model":{"node":[{"id":"attr_type","type":"string","title":"Type","values":[{"id":"ID (Keywords Plus®)","value":43,"color":"#3CC426","percentValue":100},{"id":"AU (Authors)","value":17,"color":"#D058AF","percentValue":39.53488372093023}],"minValue":17,"maxValue":43},{"id":"global_occurrences","type":"integer","title":"Occurrences Count","noDisplay":true},{"id":"attr_1_6","type":"string","title":"SO (Publication Name)","values":[{"id":"n/a","value":43,"color":"#50A3CB","percentValue":100},{"id":"PHYSICS IN PERSPECTIVE","value":4,"color":"#C8DA3C","percentValue":9.30232558139535},{"id":"POINCARE, PHILOSOPHER OF SCIENCE: PROBLEMS AND PERSPECTIVES","value":2,"color":"#E05F3D","percentValue":4.651162790697675},{"id":"PHILOSOPHY OF SCIENCE","value":2,"color":"#D26EC9","percentValue":4.651162790697675},{"id":"HISTORIA MATHEMATICA | STUDIES IN HISTORY AND PHILOSOPHY OF SCIENCE","value":1,"color":"#44CB91","percentValue":2.3255813953488373},{"id":"HISTORIA MATHEMATICA","value":1,"color":"#CA962B","percentValue":2.3255813953488373},{"id":"HENRI POINCARE, 1912-2012 | ISIS","value":1,"color":"#DF5683","percentValue":2.3255813953488373},{"id":"ISIS","value":1,"color":"#6ADC4F","percentValue":2.3255813953488373},{"id":"STUDIES IN HISTORY AND PHILOSOPHY OF MODERN PHYSICS","value":1,"color":"#8967DA","percentValue":2.3255813953488373},{"id":"PHYSICS IN PERSPECTIVE | Universe of General Relativity","value":1,"color":"#6BA13C","percentValue":2.3255813953488373},{"id":"ISIS | STUDIES IN HISTORY AND PHILOSOPHY OF MODERN PHYSICS","value":1,"color":"#aaa","percentValue":2.3255813953488373},{"id":"STUDIES IN HISTORY AND PHILOSOPHY OF SCIENCE","value":1,"color":"#aaa","percentValue":2.3255813953488373},{"id":"HISTORY AND PHILOSOPHY OF LOGIC","value":1,"color":"#aaa","percentValue":2.3255813953488373}],"minValue":4,"maxValue":43},{"id":"attr_1_7","type":"string","title":"LA (Language)","values":[{"id":"n/a","value":43,"color":"#3CC426","percentValue":100},{"id":"English","value":17,"color":"#D058AF","percentValue":39.53488372093023}],"minValue":17,"maxValue":43},{"id":"attr_1_17","type":"integer","title":"TC (Times Cited)","noDisplay":true},{"id":"attr_2_17","type":"integer","title":"TC (Times Cited) (2)","noDisplay":true}],"edge":[{"id":"attr_type","type":"string","title":"Type"},{"id":"matchings_count","type":"integer","title":"Matchings Count"}]},"lastmodifieddate":"Sun May 01 2016 19:00:26 GMT+0200 (CEST)","author":"","description":"Network extracted from a Scopus file on ScienceScape ( http://tools.medialab.sciences-po.fr/sciencescape )"},"graph":{"nodes":[{"label":"atti, l","viz":{"color":"rgb(99,124,181)","position":{"x":83.4402847290039,"y":26.06727409362793,"z":0},"size":1.262364264467491},"attributes":{"attr_type":"AU (Authors)","global_occurrences":1,"attr_1_6":"PHYSICS IN PERSPECTIVE","attr_1_7":"English","attr_1_17":3,"attr_2_17":0},"x":93.40642547607422,"y":28.486909866333008,"size":4.464101615137754,"color":"rgb(99,124,181)","id":"auauthors_a7a9e0745e49c2b69840ea8dddb65ad1","original":{"size":1.262364264467491}},{"label":"aubin, d","viz":{"color":"rgb(99,124,181)","position":{"x":-15.353837966918945,"y":-90.15718078613281,"z":0},"size":1.8329091229351038},"attributes":{"attr_type":"AU (Authors)","global_occurrences":2,"attr_1_6":"HISTORIA MATHEMATICA | STUDIES IN HISTORY AND PHILOSOPHY OF SCIENCE","attr_1_7":"English","attr_1_17":38,"attr_2_17":0},"x":-18.047876358032227,"y":-98.41295623779297,"size":8.21110255092798,"color":"rgb(99,124,181)","id":"auauthors_affa1ae90c0fd42b6fe0f8f27c15f335","original":{"size":1.8329091229351038}},{"label":"dalmedico, ad","viz":{"color":"rgb(99,124,181)","position":{"x":-33.96797180175781,"y":-67.09709930419922,"z":0},"size":1.6931471805599454},"attributes":{"attr_type":"AU (Authors)","global_occurrences":1,"attr_1_6":"HISTORIA MATHEMATICA","attr_1_7":"English","attr_1_17":38,"attr_2_17":0},"x":-37.59510040283203,"y":-76.48562622070312,"size":7.324555320336759,"color":"rgb(99,124,181)","id":"auauthors_a030e26f31f06e9783c436191380618d","original":{"size":1.6931471805599454}},{"label":"darrigol, o","viz":{"color":"rgb(99,124,181)","position":{"x":-133.6935272216797,"y":16.49555015563965,"z":0},"size":1.4054651081081644},"attributes":{"attr_type":"AU (Authors)","global_occurrences":2,"attr_1_6":"HENRI POINCARE, 1912-2012 | ISIS","attr_1_7":"English","attr_1_17":8,"attr_2_17":0},"x":-147.33126831054688,"y":15.111227035522461,"size":5.47213595499958,"color":"rgb(99,124,181)","id":"auauthors_dfeb07b3c17d7e6442e432ef9f564f72","original":{"size":1.4054651081081644}},{"label":"dragoni, g","viz":{"color":"rgb(99,124,181)","position":{"x":103.4603500366211,"y":13.199921607971191,"z":0},"size":1.262364264467491},"attributes":{"attr_type":"AU (Authors)","global_occurrences":1,"attr_1_6":"PHYSICS IN PERSPECTIVE","attr_1_7":"English","attr_1_17":3,"attr_2_17":0},"x":113.66766357421875,"y":15.14842700958252,"size":4.464101615137754,"color":"rgb(99,124,181)","id":"auauthors_b7d434d88378d544c8308c23d3426540","original":{"size":1.262364264467491}},{"label":"folina, j","viz":{"color":"rgb(99,124,181)","position":{"x":42.803016662597656,"y":88.29039764404297,"z":0},"size":1.1823215567939547},"attributes":{"attr_type":"AU (Authors)","global_occurrences":1,"attr_1_6":"POINCARE, PHILOSOPHER OF SCIENCE: PROBLEMS AND PERSPECTIVES","attr_1_7":"English","attr_1_17":0,"attr_2_17":0},"x":42.50730514526367,"y":95.67877197265625,"size":3.8284271247461903,"color":"rgb(99,124,181)","id":"auauthors_cd04b7ff8f4b86112beca169868217da","original":{"size":1.1823215567939547}},{"label":"gingras, y","viz":{"color":"rgb(99,124,181)","position":{"x":-36.97352981567383,"y":143.74002075195312,"z":0},"size":1.1823215567939547},"attributes":{"attr_type":"AU (Authors)","global_occurrences":1,"attr_1_6":"ISIS","attr_1_7":"English","attr_1_17":1,"attr_2_17":0},"x":-39.3061408996582,"y":160.7501678466797,"size":3.8284271247461903,"color":"rgb(99,124,181)","id":"auauthors_6d0ec2c19fa781b851f9f4fd1cbe1d32","original":{"size":1.1823215567939547}},{"label":"hilbert, d","viz":{"color":"rgb(99,124,181)","position":{"x":117.11100006103516,"y":-77.89840698242188,"z":0},"size":1.1823215567939547},"attributes":{"attr_type":"AU (Authors)","global_occurrences":1,"attr_1_6":"PHILOSOPHY OF SCIENCE","attr_1_7":"English","attr_1_17":0,"attr_2_17":0},"x":123.74811553955078,"y":-95.8845443725586,"size":3.8284271247461903,"color":"rgb(99,124,181)","id":"auauthors_f93d491d3ca22ae2321739d5c772ff76","original":{"size":1.1823215567939547}},{"label":"huggett, n","viz":{"color":"rgb(99,124,181)","position":{"x":104.65387725830078,"y":-87.95127868652344,"z":0},"size":1.1823215567939547},"attributes":{"attr_type":"AU (Authors)","global_occurrences":1,"attr_1_6":"PHILOSOPHY OF SCIENCE","attr_1_7":"English","attr_1_17":0,"attr_2_17":0},"x":111.45304870605469,"y":-106.29972076416016,"size":3.8284271247461903,"color":"rgb(99,124,181)","id":"auauthors_34b9be9cc6f8254529372bfcf9c462d1","original":{"size":1.1823215567939547}},{"label":"ivanova, m","viz":{"color":"rgb(99,124,181)","position":{"x":22.673065185546875,"y":146.37823486328125,"z":0},"size":1.095310179804325},"attributes":{"attr_type":"AU (Authors)","global_occurrences":1,"attr_1_6":"STUDIES IN HISTORY AND PHILOSOPHY OF MODERN PHYSICS","attr_1_7":"English","attr_1_17":0,"attr_2_17":0},"x":24.943099975585938,"y":155.52279663085938,"size":3,"color":"rgb(99,124,181)","id":"auauthors_f56c4da0b1142f459aa50ba6e6f8b87e","original":{"size":1.095310179804325}},{"label":"katzir, s","viz":{"color":"rgb(99,124,181)","position":{"x":111.59017944335938,"y":94.81829071044922,"z":0},"size":1.1823215567939547},"attributes":{"attr_type":"AU (Authors)","global_occurrences":2,"attr_1_6":"PHYSICS IN PERSPECTIVE | Universe of General Relativity","attr_1_7":"English","attr_1_17":7,"attr_2_17":0},"x":124.02603149414062,"y":110.31419372558594,"size":3.8284271247461903,"color":"rgb(99,124,181)","id":"auauthors_8465e3dd93e95da208ced7f553f7c125","original":{"size":1.1823215567939547}},{"label":"maltese, g","viz":{"color":"rgb(99,124,181)","position":{"x":92.72948455810547,"y":18.58908462524414,"z":0},"size":1.262364264467491},"attributes":{"attr_type":"AU (Authors)","global_occurrences":1,"attr_1_6":"PHYSICS IN PERSPECTIVE","attr_1_7":"English","attr_1_17":3,"attr_2_17":0},"x":103.50590515136719,"y":21.74805450439453,"size":4.464101615137754,"color":"rgb(99,124,181)","id":"auauthors_48a1e6d3a18511c42d8077be49b126d6","original":{"size":1.262364264467491}},{"label":"mawhin, j","viz":{"color":"rgb(99,124,181)","position":{"x":158.54864501953125,"y":-13.71957015991211,"z":0},"size":1.1823215567939547},"attributes":{"attr_type":"AU (Authors)","global_occurrences":2,"attr_1_6":"ISIS | STUDIES IN HISTORY AND PHILOSOPHY OF MODERN PHYSICS","attr_1_7":"English","attr_1_17":1,"attr_2_17":0},"x":172.21087646484375,"y":-23.441635131835938,"size":3.8284271247461903,"color":"rgb(99,124,181)","id":"auauthors_cc0c5a49be13000a42bda32875803540","original":{"size":1.1823215567939547}},{"label":"oberdan, t","viz":{"color":"rgb(99,124,181)","position":{"x":44.19158935546875,"y":141.25230407714844,"z":0},"size":1.1823215567939547},"attributes":{"attr_type":"AU (Authors)","global_occurrences":1,"attr_1_6":"STUDIES IN HISTORY AND PHILOSOPHY OF SCIENCE","attr_1_7":"English","attr_1_17":0,"attr_2_17":0},"x":46.732120513916016,"y":154.0640106201172,"size":3.8284271247461903,"color":"rgb(99,124,181)","id":"auauthors_b113ebc259ecb736858b565f0105bb8f","original":{"size":1.1823215567939547}},{"label":"serra, i","viz":{"color":"rgb(99,124,181)","position":{"x":-143.7308807373047,"y":-58.09782028198242,"z":0},"size":1.095310179804325},"attributes":{"attr_type":"AU (Authors)","global_occurrences":1,"attr_1_6":"POINCARE, PHILOSOPHER OF SCIENCE: PROBLEMS AND PERSPECTIVES","attr_1_7":"English","attr_1_17":0,"attr_2_17":0},"x":-155.19541931152344,"y":-70.14212799072266,"size":3,"color":"rgb(99,124,181)","id":"auauthors_3183b619298143a0ff6dda95d9224adb","original":{"size":1.095310179804325}},{"label":"stump, dj","viz":{"color":"rgb(99,124,181)","position":{"x":9.989676475524902,"y":41.87366485595703,"z":0},"size":1.1823215567939547},"attributes":{"attr_type":"AU (Authors)","global_occurrences":1,"attr_1_6":"HISTORY AND PHILOSOPHY OF LOGIC","attr_1_7":"English","attr_1_17":1,"attr_2_17":0},"x":3.018627405166626,"y":45.37067794799805,"size":3.8284271247461903,"color":"rgb(99,124,181)","id":"auauthors_9d8e55b8e89378f7637071723cd71432","original":{"size":1.1823215567939547}},{"label":"tisza, l","viz":{"color":"rgb(99,124,181)","position":{"x":-68.0233154296875,"y":77.0008544921875,"z":0},"size":1.5306282510621705},"attributes":{"attr_type":"AU (Authors)","global_occurrences":2,"attr_1_6":"PHYSICS IN PERSPECTIVE","attr_1_7":"English","attr_1_17":1,"attr_2_17":0},"x":-79.75816345214844,"y":89.53480529785156,"size":6.291502622129181,"color":"rgb(99,124,181)","id":"auauthors_e1abce216ae66a16ec23db418460784b","original":{"size":1.5306282510621705}},{"label":"3-dimensional objects","viz":{"color":"rgb(195,78,123)","position":{"x":115.6688232421875,"y":-89.11974334716797,"z":0},"size":1.1823215567939547},"attributes":{"attr_type":"ID (Keywords Plus®)","global_occurrences":1,"attr_1_6":"n/a","attr_1_7":"n/a","attr_1_17":0,"attr_2_17":0},"x":122.5114974975586,"y":-107.120849609375,"size":3.8284271247461903,"color":"rgb(195,78,123)","id":"idkeywordsplus_7b2e3057a17ed1e9019ae99f363051f4","original":{"size":1.1823215567939547}},{"label":"behavior","viz":{"color":"rgb(195,78,123)","position":{"x":-25.04939842224121,"y":-53.985958099365234,"z":0},"size":1.1823215567939547},"attributes":{"attr_type":"ID (Keywords Plus®)","global_occurrences":1,"attr_1_6":"n/a","attr_1_7":"n/a","attr_1_17":0,"attr_2_17":38},"x":-29.96622657775879,"y":-62.901771545410156,"size":3.8284271247461903,"color":"rgb(195,78,123)","id":"idkeywordsplus_b140af3d7bfd40d88d0661a887aaba80","original":{"size":1.1823215567939547}},{"label":"cambridge mathematics","viz":{"color":"rgb(195,78,123)","position":{"x":-120.39688110351562,"y":17.401506423950195,"z":0},"size":1.095310179804325},"attributes":{"attr_type":"ID (Keywords Plus®)","global_occurrences":1,"attr_1_6":"n/a","attr_1_7":"n/a","attr_1_17":0,"attr_2_17":8},"x":-133.88417053222656,"y":15.712520599365234,"size":3,"color":"rgb(195,78,123)","id":"idkeywordsplus_60e33f8da3a1181287a9f8203721ef6d","original":{"size":1.095310179804325}},{"label":"campbell","viz":{"color":"rgb(195,78,123)","position":{"x":-129.95217895507812,"y":29.58534049987793,"z":0},"size":1.095310179804325},"attributes":{"attr_type":"ID (Keywords Plus®)","global_occurrences":1,"attr_1_6":"n/a","attr_1_7":"n/a","attr_1_17":0,"attr_2_17":8},"x":-144.1160888671875,"y":28.287002563476562,"size":3,"color":"rgb(195,78,123)","id":"idkeywordsplus_3f0b8d8580d700154745170d8ff15b76","original":{"size":1.095310179804325}},{"label":"catastrophe-theory","viz":{"color":"rgb(195,78,123)","position":{"x":-39.6064338684082,"y":-91.9037857055664,"z":0},"size":1.1823215567939547},"attributes":{"attr_type":"ID (Keywords Plus®)","global_occurrences":1,"attr_1_6":"n/a","attr_1_7":"n/a","attr_1_17":0,"attr_2_17":38},"x":-44.6423225402832,"y":-103.11756896972656,"size":3.8284271247461903,"color":"rgb(195,78,123)","id":"idkeywordsplus_73b77c08cfb747b48bb885783d41620a","original":{"size":1.1823215567939547}},{"label":"cavendish physics","viz":{"color":"rgb(195,78,123)","position":{"x":-144.3400421142578,"y":24.369407653808594,"z":0},"size":1.095310179804325},"attributes":{"attr_type":"ID (Keywords Plus®)","global_occurrences":1,"attr_1_6":"n/a","attr_1_7":"n/a","attr_1_17":0,"attr_2_17":8},"x":-158.3258819580078,"y":22.978086471557617,"size":3,"color":"rgb(195,78,123)","id":"idkeywordsplus_8174a78071791a939e7c71f52f65b4ac","original":{"size":1.095310179804325}},{"label":"constancy","viz":{"color":"rgb(195,78,123)","position":{"x":99.60436248779297,"y":29.51276206970215,"z":0},"size":1.262364264467491},"attributes":{"attr_type":"ID (Keywords Plus®)","global_occurrences":1,"attr_1_6":"n/a","attr_1_7":"n/a","attr_1_17":0,"attr_2_17":3},"x":110.33220672607422,"y":31.99047088623047,"size":4.464101615137754,"color":"rgb(195,78,123)","id":"idkeywordsplus_038d7ae0de3c31debb1951520e7d5db4","original":{"size":1.262364264467491}},{"label":"convection","viz":{"color":"rgb(195,78,123)","position":{"x":-11.827117919921875,"y":-113.04419708251953,"z":0},"size":1.095310179804325},"attributes":{"attr_type":"ID (Keywords Plus®)","global_occurrences":1,"attr_1_6":"n/a","attr_1_7":"n/a","attr_1_17":0,"attr_2_17":0},"x":-12.196823120117188,"y":-122.7739486694336,"size":3,"color":"rgb(195,78,123)","id":"idkeywordsplus_cb231e090948a815d1d8185dff5c4d53","original":{"size":1.095310179804325}},{"label":"conventionalism","viz":{"color":"rgb(195,78,123)","position":{"x":-146.95614624023438,"y":-52.776206970214844,"z":0},"size":1.095310179804325},"attributes":{"attr_type":"ID (Keywords Plus®)","global_occurrences":1,"attr_1_6":"n/a","attr_1_7":"n/a","attr_1_17":0,"attr_2_17":0},"x":-157.42381286621094,"y":-64.34229278564453,"size":3,"color":"rgb(195,78,123)","id":"idkeywordsplus_b955b0902f206f04e5d5040b4ef401fb","original":{"size":1.095310179804325}},{"label":"cunningham","viz":{"color":"rgb(195,78,123)","position":{"x":-128.94850158691406,"y":3.8388254642486572,"z":0},"size":1.095310179804325},"attributes":{"attr_type":"ID (Keywords Plus®)","global_occurrences":1,"attr_1_6":"n/a","attr_1_7":"n/a","attr_1_17":0,"attr_2_17":8},"x":-142.34323120117188,"y":2.5243735313415527,"size":3,"color":"rgb(195,78,123)","id":"idkeywordsplus_caa47875b7ceacd19ff0a3fa0d7b16f0","original":{"size":1.095310179804325}},{"label":"dynamical-systems","viz":{"color":"rgb(195,78,123)","position":{"x":0.02242351695895195,"y":-108.006591796875,"z":0},"size":1.095310179804325},"attributes":{"attr_type":"ID (Keywords Plus®)","global_occurrences":1,"attr_1_6":"n/a","attr_1_7":"n/a","attr_1_17":0,"attr_2_17":0},"x":-0.9967239499092102,"y":-116.85089111328125,"size":3,"color":"rgb(195,78,123)","id":"idkeywordsplus_260bbedbe9a40172f4a1a5e0a55c0c87","original":{"size":1.095310179804325}},{"label":"dynamics","viz":{"color":"rgb(195,78,123)","position":{"x":45.84780502319336,"y":80.44109344482422,"z":0},"size":1.095310179804325},"attributes":{"attr_type":"ID (Keywords Plus®)","global_occurrences":1,"attr_1_6":"n/a","attr_1_7":"n/a","attr_1_17":0,"attr_2_17":0},"x":48.34443283081055,"y":89.47478485107422,"size":3,"color":"rgb(195,78,123)","id":"idkeywordsplus_a0e693c900663705d36be3e9e2f6c089","original":{"size":1.095310179804325}},{"label":"electron","viz":{"color":"rgb(195,78,123)","position":{"x":117.911376953125,"y":88.91722106933594,"z":0},"size":1.095310179804325},"attributes":{"attr_type":"ID (Keywords Plus®)","global_occurrences":1,"attr_1_6":"n/a","attr_1_7":"n/a","attr_1_17":0,"attr_2_17":5},"x":130.97569274902344,"y":105.08763885498047,"size":3,"color":"rgb(195,78,123)","id":"idkeywordsplus_1b85623431169fedc9a20ecf24df3f54","original":{"size":1.095310179804325}},{"label":"endomorphisms","viz":{"color":"rgb(195,78,123)","position":{"x":-3.356992244720459,"y":-75.47925567626953,"z":0},"size":1.1823215567939547},"attributes":{"attr_type":"ID (Keywords Plus®)","global_occurrences":1,"attr_1_6":"n/a","attr_1_7":"n/a","attr_1_17":0,"attr_2_17":38},"x":-6.201899528503418,"y":-83.15129852294922,"size":3.8284271247461903,"color":"rgb(195,78,123)","id":"idkeywordsplus_0ac766aa01de64a6d18be46caec9e45a","original":{"size":1.1823215567939547}},{"label":"families","viz":{"color":"rgb(195,78,123)","position":{"x":-81.75160217285156,"y":85.30740356445312,"z":0},"size":1.095310179804325},"attributes":{"attr_type":"ID (Keywords Plus®)","global_occurrences":1,"attr_1_6":"n/a","attr_1_7":"n/a","attr_1_17":0,"attr_2_17":1},"x":-93.68950653076172,"y":97.64771270751953,"size":3,"color":"rgb(195,78,123)","id":"idkeywordsplus_9df9fdb80dd531ff0f17c4754d44d995","original":{"size":1.095310179804325}},{"label":"frege","viz":{"color":"rgb(195,78,123)","position":{"x":18.564910888671875,"y":42.965660095214844,"z":0},"size":1.095310179804325},"attributes":{"attr_type":"ID (Keywords Plus®)","global_occurrences":1,"attr_1_6":"n/a","attr_1_7":"n/a","attr_1_17":0,"attr_2_17":1},"x":11.493587493896484,"y":46.45793914794922,"size":3,"color":"rgb(195,78,123)","id":"idkeywordsplus_325204ec3c4cd101cf32aeafc5953f8a","original":{"size":1.095310179804325}},{"label":"heat-transfer","viz":{"color":"rgb(195,78,123)","position":{"x":-82.76287078857422,"y":71.51913452148438,"z":0},"size":1.095310179804325},"attributes":{"attr_type":"ID (Keywords Plus®)","global_occurrences":1,"attr_1_6":"n/a","attr_1_7":"n/a","attr_1_17":0,"attr_2_17":1},"x":-94.58714294433594,"y":83.98729705810547,"size":3,"color":"rgb(195,78,123)","id":"idkeywordsplus_ca45a96cdaa400c008e65ad78f891b06","original":{"size":1.095310179804325}},{"label":"helium ii","viz":{"color":"rgb(195,78,123)","position":{"x":-52.00811004638672,"y":75.39893341064453,"z":0},"size":1.095310179804325},"attributes":{"attr_type":"ID (Keywords Plus®)","global_occurrences":1,"attr_1_6":"n/a","attr_1_7":"n/a","attr_1_17":0,"attr_2_17":1},"x":-63.73012924194336,"y":87.89344787597656,"size":3,"color":"rgb(195,78,123)","id":"idkeywordsplus_5e096cd48a9e2e6f23fbabfab752ea14","original":{"size":1.095310179804325}},{"label":"henri-poincares","viz":{"color":"rgb(195,78,123)","position":{"x":105.32678985595703,"y":100.83793640136719,"z":0},"size":1.095310179804325},"attributes":{"attr_type":"ID (Keywords Plus®)","global_occurrences":1,"attr_1_6":"n/a","attr_1_7":"n/a","attr_1_17":0,"attr_2_17":2},"x":116.92093658447266,"y":115.27238464355469,"size":3,"color":"rgb(195,78,123)","id":"idkeywordsplus_8ff8524f109d8684c149e6d0ef2f136b","original":{"size":1.095310179804325}},{"label":"hilbert","viz":{"color":"rgb(195,78,123)","position":{"x":1.5851582288742065,"y":40.454872131347656,"z":0},"size":1.095310179804325},"attributes":{"attr_type":"ID (Keywords Plus®)","global_occurrences":1,"attr_1_6":"n/a","attr_1_7":"n/a","attr_1_17":0,"attr_2_17":1},"x":-5.357054233551025,"y":43.92252731323242,"size":3,"color":"rgb(195,78,123)","id":"idkeywordsplus_2d9d7d9cb86be13d5c938e87d5a71b64","original":{"size":1.095310179804325}},{"label":"instability","viz":{"color":"rgb(195,78,123)","position":{"x":-6.878915309906006,"y":-65.2907485961914,"z":0},"size":1.1823215567939547},"attributes":{"attr_type":"ID (Keywords Plus®)","global_occurrences":1,"attr_1_6":"n/a","attr_1_7":"n/a","attr_1_17":0,"attr_2_17":38},"x":-10.065922737121582,"y":-72.95057678222656,"size":3.8284271247461903,"color":"rgb(195,78,123)","id":"idkeywordsplus_2d48c8e6528d61f80a37cdc9e33b4818","original":{"size":1.1823215567939547}},{"label":"liquid-helium","viz":{"color":"rgb(195,78,123)","position":{"x":-72.19770050048828,"y":61.61106872558594,"z":0},"size":1.095310179804325},"attributes":{"attr_type":"ID (Keywords Plus®)","global_occurrences":1,"attr_1_6":"n/a","attr_1_7":"n/a","attr_1_17":0,"attr_2_17":1},"x":-84.00951385498047,"y":74.28118896484375,"size":3,"color":"rgb(195,78,123)","id":"idkeywordsplus_64b4cf3d08416c987b58f18a3cb04eaa","original":{"size":1.095310179804325}},{"label":"mathematics","viz":{"color":"rgb(195,78,123)","position":{"x":-48.06993865966797,"y":-72.8600082397461,"z":0},"size":1.1823215567939547},"attributes":{"attr_type":"ID (Keywords Plus®)","global_occurrences":1,"attr_1_6":"n/a","attr_1_7":"n/a","attr_1_17":0,"attr_2_17":38},"x":-52.05884552001953,"y":-82.0339126586914,"size":3.8284271247461903,"color":"rgb(195,78,123)","id":"idkeywordsplus_6ae28a55456b101be8261e5dee44cd3e","original":{"size":1.1823215567939547}},{"label":"non-linear transformations","viz":{"color":"rgb(195,78,123)","position":{"x":-32.59929275512695,"y":-99.13418579101562,"z":0},"size":1.1823215567939547},"attributes":{"attr_type":"ID (Keywords Plus®)","global_occurrences":1,"attr_1_6":"n/a","attr_1_7":"n/a","attr_1_17":0,"attr_2_17":38},"x":-34.8764533996582,"y":-108.23692321777344,"size":3.8284271247461903,"color":"rgb(195,78,123)","id":"idkeywordsplus_9d15e08f10ccf606a39ecb863ed6a486","original":{"size":1.1823215567939547}},{"label":"origin","viz":{"color":"rgb(195,78,123)","position":{"x":-45.581119537353516,"y":144.8493194580078,"z":0},"size":1.095310179804325},"attributes":{"attr_type":"ID (Keywords Plus®)","global_occurrences":1,"attr_1_6":"n/a","attr_1_7":"n/a","attr_1_17":0,"attr_2_17":1},"x":-47.65015411376953,"y":163.1182403564453,"size":3,"color":"rgb(195,78,123)","id":"idkeywordsplus_7c49b153d4b59f8c0cf8c3e18dc80cb7","original":{"size":1.095310179804325}},{"label":"periodic-orbits","viz":{"color":"rgb(195,78,123)","position":{"x":161.11293029785156,"y":-5.112024307250977,"z":0},"size":1.095310179804325},"attributes":{"attr_type":"ID (Keywords Plus®)","global_occurrences":1,"attr_1_6":"n/a","attr_1_7":"n/a","attr_1_17":0,"attr_2_17":1},"x":175.10903930664062,"y":-15.090506553649902,"size":3,"color":"rgb(195,78,123)","id":"idkeywordsplus_fd4b3e8871db95203c51be7e464ca06f","original":{"size":1.095310179804325}},{"label":"realism","viz":{"color":"rgb(195,78,123)","position":{"x":31.88109016418457,"y":144.19613647460938,"z":0},"size":1.1823215567939547},"attributes":{"attr_type":"ID (Keywords Plus®)","global_occurrences":2,"attr_1_6":"n/a","attr_1_7":"n/a","attr_1_17":0,"attr_2_17":0},"x":34.33091735839844,"y":155.10397338867188,"size":3.8284271247461903,"color":"rgb(195,78,123)","id":"idkeywordsplus_d966d99d6f48e7d1c30f80600746c2de","original":{"size":1.1823215567939547}},{"label":"reason","viz":{"color":"rgb(195,78,123)","position":{"x":39.667236328125,"y":96.10940551757812,"z":0},"size":1.095310179804325},"attributes":{"attr_type":"ID (Keywords Plus®)","global_occurrences":1,"attr_1_6":"n/a","attr_1_7":"n/a","attr_1_17":0,"attr_2_17":0},"x":36.12179946899414,"y":101.37572479248047,"size":3,"color":"rgb(195,78,123)","id":"idkeywordsplus_40bea8d637cdf2c1b07fcf0630482b73","original":{"size":1.095310179804325}},{"label":"relativity","viz":{"color":"rgb(195,78,123)","position":{"x":-28.325454711914062,"y":143.50868225097656,"z":0},"size":1.095310179804325},"attributes":{"attr_type":"ID (Keywords Plus®)","global_occurrences":1,"attr_1_6":"n/a","attr_1_7":"n/a","attr_1_17":0,"attr_2_17":1},"x":-31.178016662597656,"y":157.8812713623047,"size":3,"color":"rgb(195,78,123)","id":"idkeywordsplus_8acc99eb2fceac8e027fbc1e6d60a98d","original":{"size":1.095310179804325}},{"label":"relativity 1905-1911","viz":{"color":"rgb(195,78,123)","position":{"x":-143.84951782226562,"y":7.696127414703369,"z":0},"size":1.095310179804325},"attributes":{"attr_type":"ID (Keywords Plus®)","global_occurrences":1,"attr_1_6":"n/a","attr_1_7":"n/a","attr_1_17":0,"attr_2_17":8},"x":-157.5556640625,"y":6.491962432861328,"size":3,"color":"rgb(195,78,123)","id":"idkeywordsplus_2902d3da234f36a68c04a818d6092542","original":{"size":1.095310179804325}},{"label":"renormalization-group","viz":{"color":"rgb(195,78,123)","position":{"x":-33.47749328613281,"y":-83.43252563476562,"z":0},"size":1.1823215567939547},"attributes":{"attr_type":"ID (Keywords Plus®)","global_occurrences":1,"attr_1_6":"n/a","attr_1_7":"n/a","attr_1_17":0,"attr_2_17":38},"x":-36.54744338989258,"y":-93.66783142089844,"size":3.8284271247461903,"color":"rgb(195,78,123)","id":"idkeywordsplus_ab404784131f3564521235683c536668","original":{"size":1.1823215567939547}},{"label":"researches","viz":{"color":"rgb(195,78,123)","position":{"x":93.51541900634766,"y":6.652902126312256,"z":0},"size":1.262364264467491},"attributes":{"attr_type":"ID (Keywords Plus®)","global_occurrences":1,"attr_1_6":"n/a","attr_1_7":"n/a","attr_1_17":0,"attr_2_17":3},"x":103.23388671875,"y":9.413712501525879,"size":4.464101615137754,"color":"rgb(195,78,123)","id":"idkeywordsplus_8359b03e27ae61c01ae145caf6bff0b9","original":{"size":1.262364264467491}},{"label":"rotation","viz":{"color":"rgb(195,78,123)","position":{"x":106.07322692871094,"y":-76.69072723388672,"z":0},"size":1.1823215567939547},"attributes":{"attr_type":"ID (Keywords Plus®)","global_occurrences":1,"attr_1_6":"n/a","attr_1_7":"n/a","attr_1_17":0,"attr_2_17":0},"x":112.6732177734375,"y":-95.02721405029297,"size":3.8284271247461903,"color":"rgb(195,78,123)","id":"idkeywordsplus_a5c02a3b57a78ef78fbca4f650029323","original":{"size":1.1823215567939547}},{"label":"science","viz":{"color":"rgb(195,78,123)","position":{"x":-46.34345626831055,"y":-84.22509002685547,"z":0},"size":1.1823215567939547},"attributes":{"attr_type":"ID (Keywords Plus®)","global_occurrences":1,"attr_1_6":"n/a","attr_1_7":"n/a","attr_1_17":0,"attr_2_17":38},"x":-49.40262222290039,"y":-93.30426788330078,"size":3.8284271247461903,"color":"rgb(195,78,123)","id":"idkeywordsplus_fb5c7f9bb4b32ce2f3bff4662f1ab27b","original":{"size":1.1823215567939547}},{"label":"space","viz":{"color":"rgb(195,78,123)","position":{"x":53.48562240600586,"y":139.08743286132812,"z":0},"size":1.095310179804325},"attributes":{"attr_type":"ID (Keywords Plus®)","global_occurrences":1,"attr_1_6":"n/a","attr_1_7":"n/a","attr_1_17":0,"attr_2_17":0},"x":56.09478759765625,"y":152.9136505126953,"size":3,"color":"rgb(195,78,123)","id":"idkeywordsplus_ff2364a0be3d20e46cc69efb36afe9a5","original":{"size":1.095310179804325}},{"label":"statistics","viz":{"color":"rgb(195,78,123)","position":{"x":-58.89353561401367,"y":64.0319595336914,"z":0},"size":1.095310179804325},"attributes":{"attr_type":"ID (Keywords Plus®)","global_occurrences":1,"attr_1_6":"n/a","attr_1_7":"n/a","attr_1_17":0,"attr_2_17":1},"x":-70.51821899414062,"y":76.28511047363281,"size":3,"color":"rgb(195,78,123)","id":"idkeywordsplus_a912a94d79b5124d876951f96ebb256f","original":{"size":1.095310179804325}},{"label":"superfluidity","viz":{"color":"rgb(195,78,123)","position":{"x":-56.841983795166016,"y":88.24080657958984,"z":0},"size":1.095310179804325},"attributes":{"attr_type":"ID (Keywords Plus®)","global_occurrences":1,"attr_1_6":"n/a","attr_1_7":"n/a","attr_1_17":0,"attr_2_17":1},"x":-68.65404510498047,"y":100.7600326538086,"size":3,"color":"rgb(195,78,123)","id":"idkeywordsplus_1a902125ed7d1169d5048e788d891d84","original":{"size":1.095310179804325}},{"label":"surface tension","viz":{"color":"rgb(195,78,123)","position":{"x":7.32155179977417,"y":-97.14983367919922,"z":0},"size":1.095310179804325},"attributes":{"attr_type":"ID (Keywords Plus®)","global_occurrences":1,"attr_1_6":"n/a","attr_1_7":"n/a","attr_1_17":0,"attr_2_17":0},"x":5.962374687194824,"y":-106.40381622314453,"size":3,"color":"rgb(195,78,123)","id":"idkeywordsplus_8c535f859d7280cb71c4d215aa4c2e28","original":{"size":1.095310179804325}},{"label":"system","viz":{"color":"rgb(195,78,123)","position":{"x":155.6566619873047,"y":-22.330045700073242,"z":0},"size":1.095310179804325},"attributes":{"attr_type":"ID (Keywords Plus®)","global_occurrences":1,"attr_1_6":"n/a","attr_1_7":"n/a","attr_1_17":0,"attr_2_17":1},"x":169.17637634277344,"y":-31.64216423034668,"size":3,"color":"rgb(195,78,123)","id":"idkeywordsplus_54b53072540eeeb8f8e9343e71f28176","original":{"size":1.095310179804325}},{"label":"thermodynamic equations","viz":{"color":"rgb(195,78,123)","position":{"x":-70.25016021728516,"y":92.73587799072266,"z":0},"size":1.095310179804325},"attributes":{"attr_type":"ID (Keywords Plus®)","global_occurrences":1,"attr_1_6":"n/a","attr_1_7":"n/a","attr_1_17":0,"attr_2_17":1},"x":-82.28067016601562,"y":105.20086669921875,"size":3,"color":"rgb(195,78,123)","id":"idkeywordsplus_7b63f97d3fa21444a4622129abf1d19b","original":{"size":1.095310179804325}},{"label":"transition","viz":{"color":"rgb(195,78,123)","position":{"x":-16.117633819580078,"y":-60.367881774902344,"z":0},"size":1.1823215567939547},"attributes":{"attr_type":"ID (Keywords Plus®)","global_occurrences":1,"attr_1_6":"n/a","attr_1_7":"n/a","attr_1_17":0,"attr_2_17":38},"x":-19.14816665649414,"y":-66.91695404052734,"size":3.8284271247461903,"color":"rgb(195,78,123)","id":"idkeywordsplus_1e3057527650f36abc8cfa0131920cda","original":{"size":1.1823215567939547}},{"label":"turbulence","viz":{"color":"rgb(195,78,123)","position":{"x":-17.102895736694336,"y":-72.07127380371094,"z":0},"size":1.1823215567939547},"attributes":{"attr_type":"ID (Keywords Plus®)","global_occurrences":2,"attr_1_6":"n/a","attr_1_7":"n/a","attr_1_17":0,"attr_2_17":38},"x":-20.720836639404297,"y":-79.54821014404297,"size":3.8284271247461903,"color":"rgb(195,78,123)","id":"idkeywordsplus_2aa795a3caff50241f9697d20cd2f568","original":{"size":1.1823215567939547}},{"label":"velocity","viz":{"color":"rgb(195,78,123)","position":{"x":81.92710876464844,"y":14.04499340057373,"z":0},"size":1.262364264467491},"attributes":{"attr_type":"ID (Keywords Plus®)","global_occurrences":1,"attr_1_6":"n/a","attr_1_7":"n/a","attr_1_17":0,"attr_2_17":3},"x":92.2751235961914,"y":16.68297004699707,"size":4.464101615137754,"color":"rgb(195,78,123)","id":"idkeywordsplus_ac1a453d0cdc1f19d9479ccfaa8b082c","original":{"size":1.262364264467491}}],"edges":[{"type":"directed","label":"","weight":1,"viz":{},"attributes":{"attr_type":"","matchings_count":1},"size":1,"id":"e230","source":"auauthors_a7a9e0745e49c2b69840ea8dddb65ad1","target":"idkeywordsplus_038d7ae0de3c31debb1951520e7d5db4"},{"type":"directed","label":"","weight":1,"viz":{},"attributes":{"attr_type":"","matchings_count":1},"size":1,"id":"e231","source":"auauthors_a7a9e0745e49c2b69840ea8dddb65ad1","target":"idkeywordsplus_8359b03e27ae61c01ae145caf6bff0b9"},{"type":"directed","label":"","weight":1,"viz":{},"attributes":{"attr_type":"","matchings_count":1},"size":1,"id":"e232","source":"auauthors_a7a9e0745e49c2b69840ea8dddb65ad1","target":"idkeywordsplus_ac1a453d0cdc1f19d9479ccfaa8b082c"},{"type":"directed","label":"","weight":1,"viz":{},"attributes":{"attr_type":"","matchings_count":1},"size":1,"id":"e233","source":"auauthors_affa1ae90c0fd42b6fe0f8f27c15f335","target":"idkeywordsplus_b140af3d7bfd40d88d0661a887aaba80"},{"type":"directed","label":"","weight":1,"viz":{},"attributes":{"attr_type":"","matchings_count":1},"size":1,"id":"e234","source":"auauthors_affa1ae90c0fd42b6fe0f8f27c15f335","target":"idkeywordsplus_73b77c08cfb747b48bb885783d41620a"},{"type":"directed","label":"","weight":1,"viz":{},"attributes":{"attr_type":"","matchings_count":1},"size":1,"id":"e235","source":"auauthors_affa1ae90c0fd42b6fe0f8f27c15f335","target":"idkeywordsplus_cb231e090948a815d1d8185dff5c4d53"},{"type":"directed","label":"","weight":1,"viz":{},"attributes":{"attr_type":"","matchings_count":1},"size":1,"id":"e236","source":"auauthors_affa1ae90c0fd42b6fe0f8f27c15f335","target":"idkeywordsplus_260bbedbe9a40172f4a1a5e0a55c0c87"},{"type":"directed","label":"","weight":1,"viz":{},"attributes":{"attr_type":"","matchings_count":1},"size":1,"id":"e237","source":"auauthors_affa1ae90c0fd42b6fe0f8f27c15f335","target":"idkeywordsplus_0ac766aa01de64a6d18be46caec9e45a"},{"type":"directed","label":"","weight":1,"viz":{},"attributes":{"attr_type":"","matchings_count":1},"size":1,"id":"e238","source":"auauthors_affa1ae90c0fd42b6fe0f8f27c15f335","target":"idkeywordsplus_2d48c8e6528d61f80a37cdc9e33b4818"},{"type":"directed","label":"","weight":1,"viz":{},"attributes":{"attr_type":"","matchings_count":1},"size":1,"id":"e239","source":"auauthors_affa1ae90c0fd42b6fe0f8f27c15f335","target":"idkeywordsplus_6ae28a55456b101be8261e5dee44cd3e"},{"type":"directed","label":"","weight":1,"viz":{},"attributes":{"attr_type":"","matchings_count":1},"size":1,"id":"e240","source":"auauthors_affa1ae90c0fd42b6fe0f8f27c15f335","target":"idkeywordsplus_9d15e08f10ccf606a39ecb863ed6a486"},{"type":"directed","label":"","weight":1,"viz":{},"attributes":{"attr_type":"","matchings_count":1},"size":1,"id":"e241","source":"auauthors_affa1ae90c0fd42b6fe0f8f27c15f335","target":"idkeywordsplus_ab404784131f3564521235683c536668"},{"type":"directed","label":"","weight":1,"viz":{},"attributes":{"attr_type":"","matchings_count":1},"size":1,"id":"e242","source":"auauthors_affa1ae90c0fd42b6fe0f8f27c15f335","target":"idkeywordsplus_fb5c7f9bb4b32ce2f3bff4662f1ab27b"},{"type":"directed","label":"","weight":1,"viz":{},"attributes":{"attr_type":"","matchings_count":1},"size":1,"id":"e243","source":"auauthors_affa1ae90c0fd42b6fe0f8f27c15f335","target":"idkeywordsplus_8c535f859d7280cb71c4d215aa4c2e28"},{"type":"directed","label":"","weight":1,"viz":{},"attributes":{"attr_type":"","matchings_count":1},"size":1,"id":"e244","source":"auauthors_affa1ae90c0fd42b6fe0f8f27c15f335","target":"idkeywordsplus_1e3057527650f36abc8cfa0131920cda"},{"type":"directed","label":"","weight":1,"viz":{},"attributes":{"attr_type":"","matchings_count":2},"size":1,"id":"e245","source":"auauthors_affa1ae90c0fd42b6fe0f8f27c15f335","target":"idkeywordsplus_2aa795a3caff50241f9697d20cd2f568"},{"type":"directed","label":"","weight":1,"viz":{},"attributes":{"attr_type":"","matchings_count":1},"size":1,"id":"e246","source":"auauthors_a030e26f31f06e9783c436191380618d","target":"idkeywordsplus_b140af3d7bfd40d88d0661a887aaba80"},{"type":"directed","label":"","weight":1,"viz":{},"attributes":{"attr_type":"","matchings_count":1},"size":1,"id":"e247","source":"auauthors_a030e26f31f06e9783c436191380618d","target":"idkeywordsplus_73b77c08cfb747b48bb885783d41620a"},{"type":"directed","label":"","weight":1,"viz":{},"attributes":{"attr_type":"","matchings_count":1},"size":1,"id":"e248","source":"auauthors_a030e26f31f06e9783c436191380618d","target":"idkeywordsplus_0ac766aa01de64a6d18be46caec9e45a"},{"type":"directed","label":"","weight":1,"viz":{},"attributes":{"attr_type":"","matchings_count":1},"size":1,"id":"e249","source":"auauthors_a030e26f31f06e9783c436191380618d","target":"idkeywordsplus_2d48c8e6528d61f80a37cdc9e33b4818"},{"type":"directed","label":"","weight":1,"viz":{},"attributes":{"attr_type":"","matchings_count":1},"size":1,"id":"e250","source":"auauthors_a030e26f31f06e9783c436191380618d","target":"idkeywordsplus_6ae28a55456b101be8261e5dee44cd3e"},{"type":"directed","label":"","weight":1,"viz":{},"attributes":{"attr_type":"","matchings_count":1},"size":1,"id":"e251","source":"auauthors_a030e26f31f06e9783c436191380618d","target":"idkeywordsplus_9d15e08f10ccf606a39ecb863ed6a486"},{"type":"directed","label":"","weight":1,"viz":{},"attributes":{"attr_type":"","matchings_count":1},"size":1,"id":"e252","source":"auauthors_a030e26f31f06e9783c436191380618d","target":"idkeywordsplus_ab404784131f3564521235683c536668"},{"type":"directed","label":"","weight":1,"viz":{},"attributes":{"attr_type":"","matchings_count":1},"size":1,"id":"e253","source":"auauthors_a030e26f31f06e9783c436191380618d","target":"idkeywordsplus_fb5c7f9bb4b32ce2f3bff4662f1ab27b"},{"type":"directed","label":"","weight":1,"viz":{},"attributes":{"attr_type":"","matchings_count":1},"size":1,"id":"e254","source":"auauthors_a030e26f31f06e9783c436191380618d","target":"idkeywordsplus_1e3057527650f36abc8cfa0131920cda"},{"type":"directed","label":"","weight":1,"viz":{},"attributes":{"attr_type":"","matchings_count":1},"size":1,"id":"e255","source":"auauthors_a030e26f31f06e9783c436191380618d","target":"idkeywordsplus_2aa795a3caff50241f9697d20cd2f568"},{"type":"directed","label":"","weight":1,"viz":{},"attributes":{"attr_type":"","matchings_count":1},"size":1,"id":"e256","source":"auauthors_dfeb07b3c17d7e6442e432ef9f564f72","target":"idkeywordsplus_60e33f8da3a1181287a9f8203721ef6d"},{"type":"directed","label":"","weight":1,"viz":{},"attributes":{"attr_type":"","matchings_count":1},"size":1,"id":"e257","source":"auauthors_dfeb07b3c17d7e6442e432ef9f564f72","target":"idkeywordsplus_3f0b8d8580d700154745170d8ff15b76"},{"type":"directed","label":"","weight":1,"viz":{},"attributes":{"attr_type":"","matchings_count":1},"size":1,"id":"e258","source":"auauthors_dfeb07b3c17d7e6442e432ef9f564f72","target":"idkeywordsplus_8174a78071791a939e7c71f52f65b4ac"},{"type":"directed","label":"","weight":1,"viz":{},"attributes":{"attr_type":"","matchings_count":1},"size":1,"id":"e259","source":"auauthors_dfeb07b3c17d7e6442e432ef9f564f72","target":"idkeywordsplus_caa47875b7ceacd19ff0a3fa0d7b16f0"},{"type":"directed","label":"","weight":1,"viz":{},"attributes":{"attr_type":"","matchings_count":1},"size":1,"id":"e260","source":"auauthors_dfeb07b3c17d7e6442e432ef9f564f72","target":"idkeywordsplus_2902d3da234f36a68c04a818d6092542"},{"type":"directed","label":"","weight":1,"viz":{},"attributes":{"attr_type":"","matchings_count":1},"size":1,"id":"e261","source":"auauthors_b7d434d88378d544c8308c23d3426540","target":"idkeywordsplus_038d7ae0de3c31debb1951520e7d5db4"},{"type":"directed","label":"","weight":1,"viz":{},"attributes":{"attr_type":"","matchings_count":1},"size":1,"id":"e262","source":"auauthors_b7d434d88378d544c8308c23d3426540","target":"idkeywordsplus_8359b03e27ae61c01ae145caf6bff0b9"},{"type":"directed","label":"","weight":1,"viz":{},"attributes":{"attr_type":"","matchings_count":1},"size":1,"id":"e263","source":"auauthors_b7d434d88378d544c8308c23d3426540","target":"idkeywordsplus_ac1a453d0cdc1f19d9479ccfaa8b082c"},{"type":"directed","label":"","weight":1,"viz":{},"attributes":{"attr_type":"","matchings_count":1},"size":1,"id":"e264","source":"auauthors_cd04b7ff8f4b86112beca169868217da","target":"idkeywordsplus_a0e693c900663705d36be3e9e2f6c089"},{"type":"directed","label":"","weight":1,"viz":{},"attributes":{"attr_type":"","matchings_count":1},"size":1,"id":"e265","source":"auauthors_cd04b7ff8f4b86112beca169868217da","target":"idkeywordsplus_40bea8d637cdf2c1b07fcf0630482b73"},{"type":"directed","label":"","weight":1,"viz":{},"attributes":{"attr_type":"","matchings_count":1},"size":1,"id":"e266","source":"auauthors_6d0ec2c19fa781b851f9f4fd1cbe1d32","target":"idkeywordsplus_7c49b153d4b59f8c0cf8c3e18dc80cb7"},{"type":"directed","label":"","weight":1,"viz":{},"attributes":{"attr_type":"","matchings_count":1},"size":1,"id":"e267","source":"auauthors_6d0ec2c19fa781b851f9f4fd1cbe1d32","target":"idkeywordsplus_8acc99eb2fceac8e027fbc1e6d60a98d"},{"type":"directed","label":"","weight":1,"viz":{},"attributes":{"attr_type":"","matchings_count":1},"size":1,"id":"e268","source":"auauthors_f93d491d3ca22ae2321739d5c772ff76","target":"idkeywordsplus_7b2e3057a17ed1e9019ae99f363051f4"},{"type":"directed","label":"","weight":1,"viz":{},"attributes":{"attr_type":"","matchings_count":1},"size":1,"id":"e269","source":"auauthors_f93d491d3ca22ae2321739d5c772ff76","target":"idkeywordsplus_a5c02a3b57a78ef78fbca4f650029323"},{"type":"directed","label":"","weight":1,"viz":{},"attributes":{"attr_type":"","matchings_count":1},"size":1,"id":"e270","source":"auauthors_34b9be9cc6f8254529372bfcf9c462d1","target":"idkeywordsplus_7b2e3057a17ed1e9019ae99f363051f4"},{"type":"directed","label":"","weight":1,"viz":{},"attributes":{"attr_type":"","matchings_count":1},"size":1,"id":"e271","source":"auauthors_34b9be9cc6f8254529372bfcf9c462d1","target":"idkeywordsplus_a5c02a3b57a78ef78fbca4f650029323"},{"type":"directed","label":"","weight":1,"viz":{},"attributes":{"attr_type":"","matchings_count":1},"size":1,"id":"e272","source":"auauthors_f56c4da0b1142f459aa50ba6e6f8b87e","target":"idkeywordsplus_d966d99d6f48e7d1c30f80600746c2de"},{"type":"directed","label":"","weight":1,"viz":{},"attributes":{"attr_type":"","matchings_count":1},"size":1,"id":"e273","source":"auauthors_8465e3dd93e95da208ced7f553f7c125","target":"idkeywordsplus_1b85623431169fedc9a20ecf24df3f54"},{"type":"directed","label":"","weight":1,"viz":{},"attributes":{"attr_type":"","matchings_count":1},"size":1,"id":"e274","source":"auauthors_8465e3dd93e95da208ced7f553f7c125","target":"idkeywordsplus_8ff8524f109d8684c149e6d0ef2f136b"},{"type":"directed","label":"","weight":1,"viz":{},"attributes":{"attr_type":"","matchings_count":1},"size":1,"id":"e275","source":"auauthors_48a1e6d3a18511c42d8077be49b126d6","target":"idkeywordsplus_038d7ae0de3c31debb1951520e7d5db4"},{"type":"directed","label":"","weight":1,"viz":{},"attributes":{"attr_type":"","matchings_count":1},"size":1,"id":"e276","source":"auauthors_48a1e6d3a18511c42d8077be49b126d6","target":"idkeywordsplus_8359b03e27ae61c01ae145caf6bff0b9"},{"type":"directed","label":"","weight":1,"viz":{},"attributes":{"attr_type":"","matchings_count":1},"size":1,"id":"e277","source":"auauthors_48a1e6d3a18511c42d8077be49b126d6","target":"idkeywordsplus_ac1a453d0cdc1f19d9479ccfaa8b082c"},{"type":"directed","label":"","weight":1,"viz":{},"attributes":{"attr_type":"","matchings_count":1},"size":1,"id":"e278","source":"auauthors_cc0c5a49be13000a42bda32875803540","target":"idkeywordsplus_fd4b3e8871db95203c51be7e464ca06f"},{"type":"directed","label":"","weight":1,"viz":{},"attributes":{"attr_type":"","matchings_count":1},"size":1,"id":"e279","source":"auauthors_cc0c5a49be13000a42bda32875803540","target":"idkeywordsplus_54b53072540eeeb8f8e9343e71f28176"},{"type":"directed","label":"","weight":1,"viz":{},"attributes":{"attr_type":"","matchings_count":1},"size":1,"id":"e280","source":"auauthors_b113ebc259ecb736858b565f0105bb8f","target":"idkeywordsplus_d966d99d6f48e7d1c30f80600746c2de"},{"type":"directed","label":"","weight":1,"viz":{},"attributes":{"attr_type":"","matchings_count":1},"size":1,"id":"e281","source":"auauthors_b113ebc259ecb736858b565f0105bb8f","target":"idkeywordsplus_ff2364a0be3d20e46cc69efb36afe9a5"},{"type":"directed","label":"","weight":1,"viz":{},"attributes":{"attr_type":"","matchings_count":1},"size":1,"id":"e282","source":"auauthors_3183b619298143a0ff6dda95d9224adb","target":"idkeywordsplus_b955b0902f206f04e5d5040b4ef401fb"},{"type":"directed","label":"","weight":1,"viz":{},"attributes":{"attr_type":"","matchings_count":1},"size":1,"id":"e283","source":"auauthors_9d8e55b8e89378f7637071723cd71432","target":"idkeywordsplus_325204ec3c4cd101cf32aeafc5953f8a"},{"type":"directed","label":"","weight":1,"viz":{},"attributes":{"attr_type":"","matchings_count":1},"size":1,"id":"e284","source":"auauthors_9d8e55b8e89378f7637071723cd71432","target":"idkeywordsplus_2d9d7d9cb86be13d5c938e87d5a71b64"},{"type":"directed","label":"","weight":1,"viz":{},"attributes":{"attr_type":"","matchings_count":1},"size":1,"id":"e285","source":"auauthors_e1abce216ae66a16ec23db418460784b","target":"idkeywordsplus_9df9fdb80dd531ff0f17c4754d44d995"},{"type":"directed","label":"","weight":1,"viz":{},"attributes":{"attr_type":"","matchings_count":1},"size":1,"id":"e286","source":"auauthors_e1abce216ae66a16ec23db418460784b","target":"idkeywordsplus_ca45a96cdaa400c008e65ad78f891b06"},{"type":"directed","label":"","weight":1,"viz":{},"attributes":{"attr_type":"","matchings_count":1},"size":1,"id":"e287","source":"auauthors_e1abce216ae66a16ec23db418460784b","target":"idkeywordsplus_5e096cd48a9e2e6f23fbabfab752ea14"},{"type":"directed","label":"","weight":1,"viz":{},"attributes":{"attr_type":"","matchings_count":1},"size":1,"id":"e288","source":"auauthors_e1abce216ae66a16ec23db418460784b","target":"idkeywordsplus_64b4cf3d08416c987b58f18a3cb04eaa"},{"type":"directed","label":"","weight":1,"viz":{},"attributes":{"attr_type":"","matchings_count":1},"size":1,"id":"e289","source":"auauthors_e1abce216ae66a16ec23db418460784b","target":"idkeywordsplus_a912a94d79b5124d876951f96ebb256f"},{"type":"directed","label":"","weight":1,"viz":{},"attributes":{"attr_type":"","matchings_count":1},"size":1,"id":"e290","source":"auauthors_e1abce216ae66a16ec23db418460784b","target":"idkeywordsplus_1a902125ed7d1169d5048e788d891d84"},{"type":"directed","label":"","weight":1,"viz":{},"attributes":{"attr_type":"","matchings_count":1},"size":1,"id":"e291","source":"auauthors_e1abce216ae66a16ec23db418460784b","target":"idkeywordsplus_7b63f97d3fa21444a4622129abf1d19b"}]},"snapshots":{"7925147e-931f-4356-bd64-5f4f893b6620":{"view":{"camera":{"x":0,"y":0,"ratio":1,"angle":0}},"filters":[],"id":"7925147e-931f-4356-bd64-5f4f893b6620"}}}
