{"narrative":{"title":"Cartographie","slides":[{"title":"Slide Title","text":"Cartographie Amar","snapshot":"aa1633a4-d0d8-4145-b35e-a1ac1e29b197"}],"space":"288fe9d0-9577-46bf-b8d0-babc6141d462","version":0,"type":"narrative"},"meta":{"model":{"node":[{"id":"attr_status","type":"string","title":"Status","values":[{"id":"IN","value":45,"color":"#6889AB","percentValue":100}],"minValue":45,"maxValue":45,"noDisplay":true},{"id":"attr_crawling","type":"string","title":"Crawling status","values":[],"noDisplay":true},{"id":"attr_indexing","type":"string","title":"Indexing status","values":[],"noDisplay":true},{"id":"attr_creation","type":"integer","title":"Creation","noDisplay":true},{"id":"attr_modification","type":"integer","title":"Last modification","noDisplay":true},{"id":"attr_hyphe_indegree","type":"integer","title":"Hyphe Indegree","noDisplay":true}],"edge":[{"id":"attr_count","type":"integer","title":"Hyperlinks Count"}]},"lastmodifieddate":"Fri Mar 11 2016 16:23:09 GMT+0100 (CET)","author":"","description":""},"graph":{"nodes":[{"id":"cea02a85-5805-49a7-90c9-df935656974a","label":"Monchecourt","viz":{},"attributes":{"attr_status":"IN","attr_crawling":"","attr_indexing":"","attr_creation":null,"attr_modification":null,"attr_hyphe_indegree":4},"size":7,"x":100,"y":0},{"id":"93bce2ac-b654-4373-b73c-4d4a45e29b46","label":"Amazon /.../295459540X","viz":{},"attributes":{"attr_status":"IN","attr_crawling":"","attr_indexing":"","attr_creation":null,"attr_modification":null,"attr_hyphe_indegree":3},"size":9.246211251235321,"x":99.02680687415703,"y":13.917310096006544},{"id":"dacdecec-b628-4b5e-b115-1100005c8823","label":"Societe /.../monsieur-antoine-monchecourt-507930592.html","viz":{},"attributes":{"attr_status":"IN","attr_crawling":"","attr_indexing":"","attr_creation":null,"attr_modification":null,"attr_hyphe_indegree":1},"size":3.8284271247461903,"x":96.12616959383189,"y":27.563735581699916},{"id":"9ec82976-9548-4e12-8c54-fae2e7edca10","label":"Aquinum /.../Antoine Monchecourt","viz":{},"attributes":{"attr_status":"IN","attr_crawling":"","attr_indexing":"","attr_creation":null,"attr_modification":null,"attr_hyphe_indegree":1},"size":3,"x":91.35454576426008,"y":40.67366430758001},{"id":"63dedef4-3806-462a-b93d-c7dbf6dab351","label":"dirigeants.Bfmtv /Antoine-MONCHECOURT-421995","viz":{},"attributes":{"attr_status":"IN","attr_crawling":"","attr_indexing":"","attr_creation":null,"attr_modification":null,"attr_hyphe_indegree":1},"size":3.8284271247461903,"x":84.8048096156426,"y":52.99192642332049},{"id":"114169b0-618d-4f62-b82c-21d92584efcc","label":"antoinemonchecourt.blog.Lemonde","viz":{},"attributes":{"attr_status":"IN","attr_crawling":"","attr_indexing":"","attr_creation":null,"attr_modification":null,"attr_hyphe_indegree":1},"size":3,"x":76.60444431189781,"y":64.27876096865393},{"id":"2b961528-5751-446f-ab7b-f8da6258370f","label":"Twitter /amonchecourt","viz":{},"attributes":{"attr_status":"IN","attr_crawling":"","attr_indexing":"","attr_creation":null,"attr_modification":null,"attr_hyphe_indegree":2},"size":5.898979485566356,"x":66.91306063588583,"y":74.31448254773943},{"id":"2026447d-49df-4fec-8c13-b5ae0c59986a","label":"u-bordeaux3.Academia /AntoineMonchecourt","viz":{},"attributes":{"attr_status":"IN","attr_crawling":"","attr_indexing":"","attr_creation":null,"attr_modification":null,"attr_hyphe_indegree":0},"size":1,"x":55.91929034707468,"y":82.90375725550417},{"id":"29de0196-37d3-4926-aa67-7602e9c7c71a","label":"Etsy /.../TableauxAbstraits","viz":{},"attributes":{"attr_status":"IN","attr_crawling":"","attr_indexing":"","attr_creation":null,"attr_modification":null,"attr_hyphe_indegree":1},"size":3,"x":43.837114678907746,"y":89.8794046299167},{"id":"6538d49f-2b8d-46f3-89d7-0f98a06dc5c2","label":"Linkedin /.../fr","viz":{},"attributes":{"attr_status":"IN","attr_crawling":"","attr_indexing":"","attr_creation":null,"attr_modification":null,"attr_hyphe_indegree":2},"size":6.291502622129181,"x":30.901699437494745,"y":95.10565162951535},{"id":"bde04a0a-ab6f-42b6-ad69-9f0030c18709","label":"Facebook /antoine.monchecourt","viz":{},"attributes":{"attr_status":"IN","attr_crawling":"","attr_indexing":"","attr_creation":null,"attr_modification":null,"attr_hyphe_indegree":2},"size":3,"x":17.36481776669304,"y":98.4807753012208},{"id":"1b24fcd8-6507-44f6-8696-ce226f3a818b","label":"Linkedin /.../fr ?locale=fr_FR&trk=profile_view_lang_sel_click","viz":{},"attributes":{"attr_status":"IN","attr_crawling":"","attr_indexing":"","attr_creation":null,"attr_modification":null,"attr_hyphe_indegree":0},"size":6.291502622129181,"x":3.489949670250108,"y":99.93908270190957},{"id":"54791f96-11d1-4a0a-8761-1897b1f31837","label":"itunes.Apple /.../id881904500","viz":{},"attributes":{"attr_status":"IN","attr_crawling":"","attr_indexing":"","attr_creation":null,"attr_modification":null,"attr_hyphe_indegree":1},"size":3,"x":-10.452846326765334,"y":99.45218953682733},{"id":"220d9d56-f534-453f-89dd-34ed46633db3","label":"Viadeo /.../edit ?viewType=main","viz":{},"attributes":{"attr_status":"IN","attr_crawling":"","attr_indexing":"","attr_creation":null,"attr_modification":null,"attr_hyphe_indegree":0},"size":1,"x":-24.192189559966778,"y":97.02957262759965},{"id":"41d4b08c-2c04-4fc9-b2e0-067785094956","label":"Amazon /.../B017BVW96S","viz":{},"attributes":{"attr_status":"IN","attr_crawling":"","attr_indexing":"","attr_creation":null,"attr_modification":null,"attr_hyphe_indegree":1},"size":8.745966692414834,"x":-37.46065934159121,"y":92.71838545667875},{"id":"9ecdaa48-fef4-4704-9b32-9ca64c4b60aa","label":"Hopwork /.../antoinemonchecourt","viz":{},"attributes":{"attr_status":"IN","attr_crawling":"","attr_indexing":"","attr_creation":null,"attr_modification":null,"attr_hyphe_indegree":1},"size":1,"x":-49.99999999999998,"y":86.60254037844388},{"id":"c8983b72-3f60-4f05-8bdc-20abf3308f0f","label":"plus.Google /+AntoineMONCHECOURT","viz":{},"attributes":{"attr_status":"IN","attr_crawling":"","attr_indexing":"","attr_creation":null,"attr_modification":null,"attr_hyphe_indegree":1},"size":5,"x":-61.56614753256583,"y":78.8010753606722},{"id":"8013c65b-d8c6-4a60-9312-54f055ac9ed0","label":"journal.Projet-Ux","viz":{},"attributes":{"attr_status":"IN","attr_crawling":"","attr_indexing":"","attr_creation":null,"attr_modification":null,"attr_hyphe_indegree":3},"size":5,"x":-71.93398003386513,"y":69.46583704589972},{"id":"706b50e6-0c7f-453e-b46e-2fa54868571e","label":"Researchgate /.../Antoine_Monchecourt","viz":{},"attributes":{"attr_status":"IN","attr_crawling":"","attr_indexing":"","attr_creation":null,"attr_modification":null,"attr_hyphe_indegree":1},"size":1,"x":-80.90169943749474,"y":58.77852522924732},{"id":"002d11b0-aeca-46fd-a70c-b5503ab74bae","label":"Facebook /unsupportedbrowser","viz":{},"attributes":{"attr_status":"IN","attr_crawling":"","attr_indexing":"","attr_creation":null,"attr_modification":null,"attr_hyphe_indegree":2},"size":3.8284271247461903,"x":-88.29475928589268,"y":46.947156278589105},{"id":"1bc8043a-2abe-4888-b0ad-e842801e135d","label":"Linkedin","viz":{},"attributes":{"attr_status":"IN","attr_crawling":"","attr_indexing":"","attr_creation":null,"attr_modification":null,"attr_hyphe_indegree":2},"size":3.8284271247461903,"x":-93.96926207859083,"y":34.20201433256689},{"id":"b2eaa4e6-8a43-4ce1-ab76-cf14f1d45441","label":"Linkedin /... /ajax","viz":{},"attributes":{"attr_status":"IN","attr_crawling":"","attr_indexing":"","attr_creation":null,"attr_modification":null,"attr_hyphe_indegree":2},"size":3.8284271247461903,"x":-97.81476007338057,"y":20.79116908177593},{"id":"6c77f201-200b-49ed-b775-24c1fed26caf","label":"Linkedin /... /css","viz":{},"attributes":{"attr_status":"IN","attr_crawling":"","attr_indexing":"","attr_creation":null,"attr_modification":null,"attr_hyphe_indegree":2},"size":3.8284271247461903,"x":-99.75640502598242,"y":6.975647374412553},{"id":"9596ae74-cfb3-4185-877a-a39e52a81775","label":"Linkedin /... /asp.net","viz":{},"attributes":{"attr_status":"IN","attr_crawling":"","attr_indexing":"","attr_creation":null,"attr_modification":null,"attr_hyphe_indegree":2},"size":3.8284271247461903,"x":-99.75640502598243,"y":-6.975647374412483},{"id":"5c1f89a3-dfd4-4f73-b851-8f54b936c8fa","label":"Linkedin /... /antoinemonchecourt","viz":{},"attributes":{"attr_status":"IN","attr_crawling":"","attr_indexing":"","attr_creation":null,"attr_modification":null,"attr_hyphe_indegree":2},"size":3.8284271247461903,"x":-97.81476007338057,"y":-20.791169081775905},{"id":"8ba8674c-2b78-493c-9e93-2413b6abed41","label":"Linkedin /... /apache","viz":{},"attributes":{"attr_status":"IN","attr_crawling":"","attr_indexing":"","attr_creation":null,"attr_modification":null,"attr_hyphe_indegree":2},"size":3.8284271247461903,"x":-93.96926207859084,"y":-34.20201433256687},{"id":"3745d04c-cc04-47b7-a5c4-0ab4d07940f4","label":"Instagram","viz":{},"attributes":{"attr_status":"IN","attr_crawling":"","attr_indexing":"","attr_creation":null,"attr_modification":null,"attr_hyphe_indegree":2},"size":3.8284271247461903,"x":-88.29475928589268,"y":-46.947156278589084},{"id":"83d1498c-6e36-4049-9055-57fa1dbbab39","label":"Amazon","viz":{},"attributes":{"attr_status":"IN","attr_crawling":"","attr_indexing":"","attr_creation":null,"attr_modification":null,"attr_hyphe_indegree":2},"size":3.8284271247461903,"x":-80.90169943749474,"y":-58.7785252292473},{"id":"44774231-db27-4b77-93e5-5338da4dfc20","label":"Amazon","viz":{},"attributes":{"attr_status":"IN","attr_crawling":"","attr_indexing":"","attr_creation":null,"attr_modification":null,"attr_hyphe_indegree":3},"size":4.464101615137754,"x":-71.93398003386511,"y":-69.46583704589973},{"id":"8d991367-2ef5-40de-9449-337d74450ce1","label":"Amazon","viz":{},"attributes":{"attr_status":"IN","attr_crawling":"","attr_indexing":"","attr_creation":null,"attr_modification":null,"attr_hyphe_indegree":2},"size":3.8284271247461903,"x":-61.56614753256581,"y":-78.80107536067221},{"id":"4d470664-a47a-4208-b4b6-3efdd3608968","label":"Amazon","viz":{},"attributes":{"attr_status":"IN","attr_crawling":"","attr_indexing":"","attr_creation":null,"attr_modification":null,"attr_hyphe_indegree":2},"size":3.8284271247461903,"x":-50.00000000000004,"y":-86.60254037844383},{"id":"66d85b42-69f2-49aa-9b7d-6d1b8f85fb5a","label":"Amazon","viz":{},"attributes":{"attr_status":"IN","attr_crawling":"","attr_indexing":"","attr_creation":null,"attr_modification":null,"attr_hyphe_indegree":2},"size":3.8284271247461903,"x":-37.46065934159123,"y":-92.71838545667873},{"id":"e6e26f1f-bad1-4540-b426-ca95f337f069","label":"Amazon","viz":{},"attributes":{"attr_status":"IN","attr_crawling":"","attr_indexing":"","attr_creation":null,"attr_modification":null,"attr_hyphe_indegree":4},"size":5,"x":-24.192189559966778,"y":-97.02957262759965},{"id":"af9db6cd-99b9-4706-a465-3ea518e68660","label":"Amazon","viz":{},"attributes":{"attr_status":"IN","attr_crawling":"","attr_indexing":"","attr_creation":null,"attr_modification":null,"attr_hyphe_indegree":2},"size":3.8284271247461903,"x":-10.452846326765336,"y":-99.45218953682733},{"id":"72af152f-e1ea-4d6a-ac41-a7b92c96aab6","label":"Amazon","viz":{},"attributes":{"attr_status":"IN","attr_crawling":"","attr_indexing":"","attr_creation":null,"attr_modification":null,"attr_hyphe_indegree":2},"size":3.8284271247461903,"x":3.489949670250128,"y":-99.93908270190957},{"id":"a590fcfe-39bb-40ad-8de9-70533235912e","label":"Amazon","viz":{},"attributes":{"attr_status":"IN","attr_crawling":"","attr_indexing":"","attr_creation":null,"attr_modification":null,"attr_hyphe_indegree":2},"size":3.8284271247461903,"x":17.364817766692997,"y":-98.48077530122082},{"id":"1cea6d1c-2351-4015-b1d3-60950fb858f4","label":"Amazon","viz":{},"attributes":{"attr_status":"IN","attr_crawling":"","attr_indexing":"","attr_creation":null,"attr_modification":null,"attr_hyphe_indegree":2},"size":3.8284271247461903,"x":30.901699437494724,"y":-95.10565162951536},{"id":"4db95da3-78a5-4b9e-b305-5465612725cd","label":"Amazon","viz":{},"attributes":{"attr_status":"IN","attr_crawling":"","attr_indexing":"","attr_creation":null,"attr_modification":null,"attr_hyphe_indegree":2},"size":3.8284271247461903,"x":43.83711467890774,"y":-89.8794046299167},{"id":"9bf5ec55-4437-429a-81d4-e5ff415f868b","label":"Bookdepository","viz":{},"attributes":{"attr_status":"IN","attr_crawling":"","attr_indexing":"","attr_creation":null,"attr_modification":null,"attr_hyphe_indegree":2},"size":3.8284271247461903,"x":55.91929034707462,"y":-82.9037572555042},{"id":"a0e2894a-ebf2-4aff-9fac-b3cb2ebf6946","label":"Amazon","viz":{},"attributes":{"attr_status":"IN","attr_crawling":"","attr_indexing":"","attr_creation":null,"attr_modification":null,"attr_hyphe_indegree":2},"size":3.8284271247461903,"x":66.91306063588578,"y":-74.31448254773946},{"id":"23c12f87-5e22-4c96-9672-149fe3e62a3d","label":"Amazon","viz":{},"attributes":{"attr_status":"IN","attr_crawling":"","attr_indexing":"","attr_creation":null,"attr_modification":null,"attr_hyphe_indegree":2},"size":3.8284271247461903,"x":76.6044443118978,"y":-64.27876096865396},{"id":"85f47b33-90fc-40e4-9039-ef007b6961b1","label":"Amazon","viz":{},"attributes":{"attr_status":"IN","attr_crawling":"","attr_indexing":"","attr_creation":null,"attr_modification":null,"attr_hyphe_indegree":2},"size":3.8284271247461903,"x":84.80480961564254,"y":-52.99192642332058},{"id":"5cb4c54d-0ace-458f-a406-6c7744e250f2","label":"Apple","viz":{},"attributes":{"attr_status":"IN","attr_crawling":"","attr_indexing":"","attr_creation":null,"attr_modification":null,"attr_hyphe_indegree":2},"size":3.8284271247461903,"x":91.3545457642601,"y":-40.67366430758001},{"id":"4ee24a10-42bc-4386-a5fb-983456473ef6","label":"Plus.Google /u","viz":{},"attributes":{"attr_status":"IN","attr_crawling":"","attr_indexing":"","attr_creation":null,"attr_modification":null,"attr_hyphe_indegree":4},"size":5,"x":96.12616959383186,"y":-27.563735581699977},{"id":"51277a5b-abca-424b-bde8-b8c36027010e","label":"Google","viz":{},"attributes":{"attr_status":"IN","attr_crawling":"","attr_indexing":"","attr_creation":null,"attr_modification":null,"attr_hyphe_indegree":3},"size":4.464101615137754,"x":99.02680687415703,"y":-13.917310096006588}],"edges":[{"id":"e0","type":"directed","label":"","source":"1b24fcd8-6507-44f6-8696-ce226f3a818b","target":"5c1f89a3-dfd4-4f73-b851-8f54b936c8fa","weight":1,"viz":{},"attributes":{"attr_count":5},"size":1},{"id":"e1","type":"directed","label":"","source":"1b24fcd8-6507-44f6-8696-ce226f3a818b","target":"6538d49f-2b8d-46f3-89d7-0f98a06dc5c2","weight":1,"viz":{},"attributes":{"attr_count":3},"size":1},{"id":"e2","type":"directed","label":"","source":"1b24fcd8-6507-44f6-8696-ce226f3a818b","target":"8ba8674c-2b78-493c-9e93-2413b6abed41","weight":1,"viz":{},"attributes":{"attr_count":3},"size":1},{"id":"e3","type":"directed","label":"","source":"1b24fcd8-6507-44f6-8696-ce226f3a818b","target":"1bc8043a-2abe-4888-b0ad-e842801e135d","weight":1,"viz":{},"attributes":{"attr_count":49},"size":1},{"id":"e4","type":"directed","label":"","source":"1b24fcd8-6507-44f6-8696-ce226f3a818b","target":"b2eaa4e6-8a43-4ce1-ab76-cf14f1d45441","weight":1,"viz":{},"attributes":{"attr_count":3},"size":1},{"id":"e5","type":"directed","label":"","source":"1b24fcd8-6507-44f6-8696-ce226f3a818b","target":"6c77f201-200b-49ed-b775-24c1fed26caf","weight":1,"viz":{},"attributes":{"attr_count":3},"size":1},{"id":"e6","type":"directed","label":"","source":"1b24fcd8-6507-44f6-8696-ce226f3a818b","target":"9596ae74-cfb3-4185-877a-a39e52a81775","weight":1,"viz":{},"attributes":{"attr_count":3},"size":1},{"id":"e7","type":"directed","label":"","source":"6538d49f-2b8d-46f3-89d7-0f98a06dc5c2","target":"b2eaa4e6-8a43-4ce1-ab76-cf14f1d45441","weight":1,"viz":{},"attributes":{"attr_count":3},"size":1},{"id":"e8","type":"directed","label":"","source":"6538d49f-2b8d-46f3-89d7-0f98a06dc5c2","target":"8ba8674c-2b78-493c-9e93-2413b6abed41","weight":1,"viz":{},"attributes":{"attr_count":3},"size":1},{"id":"e9","type":"directed","label":"","source":"6538d49f-2b8d-46f3-89d7-0f98a06dc5c2","target":"1bc8043a-2abe-4888-b0ad-e842801e135d","weight":1,"viz":{},"attributes":{"attr_count":49},"size":1},{"id":"e10","type":"directed","label":"","source":"6538d49f-2b8d-46f3-89d7-0f98a06dc5c2","target":"5c1f89a3-dfd4-4f73-b851-8f54b936c8fa","weight":1,"viz":{},"attributes":{"attr_count":5},"size":1},{"id":"e11","type":"directed","label":"","source":"6538d49f-2b8d-46f3-89d7-0f98a06dc5c2","target":"6c77f201-200b-49ed-b775-24c1fed26caf","weight":1,"viz":{},"attributes":{"attr_count":3},"size":1},{"id":"e12","type":"directed","label":"","source":"6538d49f-2b8d-46f3-89d7-0f98a06dc5c2","target":"9596ae74-cfb3-4185-877a-a39e52a81775","weight":1,"viz":{},"attributes":{"attr_count":3},"size":1},{"id":"e13","type":"directed","label":"","source":"2b961528-5751-446f-ab7b-f8da6258370f","target":"8013c65b-d8c6-4a60-9312-54f055ac9ed0","weight":1,"viz":{},"attributes":{"attr_count":1498},"size":1},{"id":"e14","type":"directed","label":"","source":"2b961528-5751-446f-ab7b-f8da6258370f","target":"002d11b0-aeca-46fd-a70c-b5503ab74bae","weight":1,"viz":{},"attributes":{"attr_count":82},"size":1},{"id":"e15","type":"directed","label":"","source":"2b961528-5751-446f-ab7b-f8da6258370f","target":"cea02a85-5805-49a7-90c9-df935656974a","weight":1,"viz":{},"attributes":{"attr_count":45},"size":1},{"id":"e16","type":"directed","label":"","source":"2b961528-5751-446f-ab7b-f8da6258370f","target":"93bce2ac-b654-4373-b73c-4d4a45e29b46","weight":1,"viz":{},"attributes":{"attr_count":139},"size":1},{"id":"e17","type":"directed","label":"","source":"2b961528-5751-446f-ab7b-f8da6258370f","target":"3745d04c-cc04-47b7-a5c4-0ab4d07940f4","weight":1,"viz":{},"attributes":{"attr_count":7},"size":1},{"id":"e18","type":"directed","label":"","source":"cea02a85-5805-49a7-90c9-df935656974a","target":"44774231-db27-4b77-93e5-5338da4dfc20","weight":1,"viz":{},"attributes":{"attr_count":3},"size":1},{"id":"e19","type":"directed","label":"","source":"cea02a85-5805-49a7-90c9-df935656974a","target":"4ee24a10-42bc-4386-a5fb-983456473ef6","weight":1,"viz":{},"attributes":{"attr_count":9},"size":1},{"id":"e20","type":"directed","label":"","source":"cea02a85-5805-49a7-90c9-df935656974a","target":"2b961528-5751-446f-ab7b-f8da6258370f","weight":1,"viz":{},"attributes":{"attr_count":9},"size":1},{"id":"e21","type":"directed","label":"","source":"cea02a85-5805-49a7-90c9-df935656974a","target":"93bce2ac-b654-4373-b73c-4d4a45e29b46","weight":1,"viz":{},"attributes":{"attr_count":3},"size":1},{"id":"e22","type":"directed","label":"","source":"cea02a85-5805-49a7-90c9-df935656974a","target":"bde04a0a-ab6f-42b6-ad69-9f0030c18709","weight":1,"viz":{},"attributes":{"attr_count":16},"size":1},{"id":"e23","type":"directed","label":"","source":"cea02a85-5805-49a7-90c9-df935656974a","target":"e6e26f1f-bad1-4540-b426-ca95f337f069","weight":1,"viz":{},"attributes":{"attr_count":3},"size":1},{"id":"e24","type":"directed","label":"","source":"dacdecec-b628-4b5e-b115-1100005c8823","target":"5cb4c54d-0ace-458f-a406-6c7744e250f2","weight":1,"viz":{},"attributes":{"attr_count":5},"size":1},{"id":"e25","type":"directed","label":"","source":"dacdecec-b628-4b5e-b115-1100005c8823","target":"51277a5b-abca-424b-bde8-b8c36027010e","weight":1,"viz":{},"attributes":{"attr_count":3},"size":1},{"id":"e26","type":"directed","label":"","source":"8013c65b-d8c6-4a60-9312-54f055ac9ed0","target":"cea02a85-5805-49a7-90c9-df935656974a","weight":1,"viz":{},"attributes":{"attr_count":3},"size":1},{"id":"e27","type":"directed","label":"","source":"8013c65b-d8c6-4a60-9312-54f055ac9ed0","target":"4ee24a10-42bc-4386-a5fb-983456473ef6","weight":1,"viz":{},"attributes":{"attr_count":3},"size":1},{"id":"e28","type":"directed","label":"","source":"114169b0-618d-4f62-b82c-21d92584efcc","target":"002d11b0-aeca-46fd-a70c-b5503ab74bae","weight":1,"viz":{},"attributes":{"attr_count":19},"size":1},{"id":"e29","type":"directed","label":"","source":"54791f96-11d1-4a0a-8761-1897b1f31837","target":"5cb4c54d-0ace-458f-a406-6c7744e250f2","weight":1,"viz":{},"attributes":{"attr_count":119},"size":1},{"id":"e30","type":"directed","label":"","source":"41d4b08c-2c04-4fc9-b2e0-067785094956","target":"8d991367-2ef5-40de-9449-337d74450ce1","weight":1,"viz":{},"attributes":{"attr_count":7},"size":1},{"id":"e31","type":"directed","label":"","source":"41d4b08c-2c04-4fc9-b2e0-067785094956","target":"4db95da3-78a5-4b9e-b305-5465612725cd","weight":1,"viz":{},"attributes":{"attr_count":7},"size":1},{"id":"e32","type":"directed","label":"","source":"41d4b08c-2c04-4fc9-b2e0-067785094956","target":"1cea6d1c-2351-4015-b1d3-60950fb858f4","weight":1,"viz":{},"attributes":{"attr_count":7},"size":1},{"id":"e33","type":"directed","label":"","source":"41d4b08c-2c04-4fc9-b2e0-067785094956","target":"83d1498c-6e36-4049-9055-57fa1dbbab39","weight":1,"viz":{},"attributes":{"attr_count":7},"size":1},{"id":"e34","type":"directed","label":"","source":"41d4b08c-2c04-4fc9-b2e0-067785094956","target":"af9db6cd-99b9-4706-a465-3ea518e68660","weight":1,"viz":{},"attributes":{"attr_count":7},"size":1},{"id":"e35","type":"directed","label":"","source":"41d4b08c-2c04-4fc9-b2e0-067785094956","target":"23c12f87-5e22-4c96-9672-149fe3e62a3d","weight":1,"viz":{},"attributes":{"attr_count":7},"size":1},{"id":"e36","type":"directed","label":"","source":"41d4b08c-2c04-4fc9-b2e0-067785094956","target":"66d85b42-69f2-49aa-9b7d-6d1b8f85fb5a","weight":1,"viz":{},"attributes":{"attr_count":7},"size":1},{"id":"e37","type":"directed","label":"","source":"41d4b08c-2c04-4fc9-b2e0-067785094956","target":"44774231-db27-4b77-93e5-5338da4dfc20","weight":1,"viz":{},"attributes":{"attr_count":643},"size":1},{"id":"e38","type":"directed","label":"","source":"41d4b08c-2c04-4fc9-b2e0-067785094956","target":"72af152f-e1ea-4d6a-ac41-a7b92c96aab6","weight":1,"viz":{},"attributes":{"attr_count":7},"size":1},{"id":"e39","type":"directed","label":"","source":"41d4b08c-2c04-4fc9-b2e0-067785094956","target":"4d470664-a47a-4208-b4b6-3efdd3608968","weight":1,"viz":{},"attributes":{"attr_count":7},"size":1},{"id":"e40","type":"directed","label":"","source":"41d4b08c-2c04-4fc9-b2e0-067785094956","target":"a590fcfe-39bb-40ad-8de9-70533235912e","weight":1,"viz":{},"attributes":{"attr_count":7},"size":1},{"id":"e41","type":"directed","label":"","source":"41d4b08c-2c04-4fc9-b2e0-067785094956","target":"e6e26f1f-bad1-4540-b426-ca95f337f069","weight":1,"viz":{},"attributes":{"attr_count":7},"size":1},{"id":"e42","type":"directed","label":"","source":"41d4b08c-2c04-4fc9-b2e0-067785094956","target":"85f47b33-90fc-40e4-9039-ef007b6961b1","weight":1,"viz":{},"attributes":{"attr_count":7},"size":1},{"id":"e43","type":"directed","label":"","source":"41d4b08c-2c04-4fc9-b2e0-067785094956","target":"9bf5ec55-4437-429a-81d4-e5ff415f868b","weight":1,"viz":{},"attributes":{"attr_count":7},"size":1},{"id":"e44","type":"directed","label":"","source":"41d4b08c-2c04-4fc9-b2e0-067785094956","target":"a0e2894a-ebf2-4aff-9fac-b3cb2ebf6946","weight":1,"viz":{},"attributes":{"attr_count":7},"size":1},{"id":"e45","type":"directed","label":"","source":"29de0196-37d3-4926-aa67-7602e9c7c71a","target":"3745d04c-cc04-47b7-a5c4-0ab4d07940f4","weight":1,"viz":{},"attributes":{"attr_count":19},"size":1},{"id":"e46","type":"directed","label":"","source":"9ec82976-9548-4e12-8c54-fae2e7edca10","target":"4ee24a10-42bc-4386-a5fb-983456473ef6","weight":1,"viz":{},"attributes":{"attr_count":4},"size":1},{"id":"e47","type":"directed","label":"","source":"63dedef4-3806-462a-b93d-c7dbf6dab351","target":"4ee24a10-42bc-4386-a5fb-983456473ef6","weight":1,"viz":{},"attributes":{"attr_count":7},"size":1},{"id":"e48","type":"directed","label":"","source":"63dedef4-3806-462a-b93d-c7dbf6dab351","target":"51277a5b-abca-424b-bde8-b8c36027010e","weight":1,"viz":{},"attributes":{"attr_count":10},"size":1},{"id":"e49","type":"directed","label":"","source":"93bce2ac-b654-4373-b73c-4d4a45e29b46","target":"83d1498c-6e36-4049-9055-57fa1dbbab39","weight":1,"viz":{},"attributes":{"attr_count":3},"size":1},{"id":"e50","type":"directed","label":"","source":"93bce2ac-b654-4373-b73c-4d4a45e29b46","target":"4db95da3-78a5-4b9e-b305-5465612725cd","weight":1,"viz":{},"attributes":{"attr_count":3},"size":1},{"id":"e51","type":"directed","label":"","source":"93bce2ac-b654-4373-b73c-4d4a45e29b46","target":"72af152f-e1ea-4d6a-ac41-a7b92c96aab6","weight":1,"viz":{},"attributes":{"attr_count":3},"size":1},{"id":"e52","type":"directed","label":"","source":"93bce2ac-b654-4373-b73c-4d4a45e29b46","target":"8d991367-2ef5-40de-9449-337d74450ce1","weight":1,"viz":{},"attributes":{"attr_count":3},"size":1},{"id":"e53","type":"directed","label":"","source":"93bce2ac-b654-4373-b73c-4d4a45e29b46","target":"66d85b42-69f2-49aa-9b7d-6d1b8f85fb5a","weight":1,"viz":{},"attributes":{"attr_count":3},"size":1},{"id":"e54","type":"directed","label":"","source":"93bce2ac-b654-4373-b73c-4d4a45e29b46","target":"85f47b33-90fc-40e4-9039-ef007b6961b1","weight":1,"viz":{},"attributes":{"attr_count":3},"size":1},{"id":"e55","type":"directed","label":"","source":"93bce2ac-b654-4373-b73c-4d4a45e29b46","target":"44774231-db27-4b77-93e5-5338da4dfc20","weight":1,"viz":{},"attributes":{"attr_count":7},"size":1},{"id":"e56","type":"directed","label":"","source":"93bce2ac-b654-4373-b73c-4d4a45e29b46","target":"9bf5ec55-4437-429a-81d4-e5ff415f868b","weight":1,"viz":{},"attributes":{"attr_count":3},"size":1},{"id":"e57","type":"directed","label":"","source":"93bce2ac-b654-4373-b73c-4d4a45e29b46","target":"e6e26f1f-bad1-4540-b426-ca95f337f069","weight":1,"viz":{},"attributes":{"attr_count":353},"size":1},{"id":"e58","type":"directed","label":"","source":"93bce2ac-b654-4373-b73c-4d4a45e29b46","target":"a590fcfe-39bb-40ad-8de9-70533235912e","weight":1,"viz":{},"attributes":{"attr_count":3},"size":1},{"id":"e59","type":"directed","label":"","source":"93bce2ac-b654-4373-b73c-4d4a45e29b46","target":"a0e2894a-ebf2-4aff-9fac-b3cb2ebf6946","weight":1,"viz":{},"attributes":{"attr_count":3},"size":1},{"id":"e60","type":"directed","label":"","source":"93bce2ac-b654-4373-b73c-4d4a45e29b46","target":"4d470664-a47a-4208-b4b6-3efdd3608968","weight":1,"viz":{},"attributes":{"attr_count":3},"size":1},{"id":"e61","type":"directed","label":"","source":"93bce2ac-b654-4373-b73c-4d4a45e29b46","target":"af9db6cd-99b9-4706-a465-3ea518e68660","weight":1,"viz":{},"attributes":{"attr_count":3},"size":1},{"id":"e62","type":"directed","label":"","source":"93bce2ac-b654-4373-b73c-4d4a45e29b46","target":"23c12f87-5e22-4c96-9672-149fe3e62a3d","weight":1,"viz":{},"attributes":{"attr_count":3},"size":1},{"id":"e63","type":"directed","label":"","source":"93bce2ac-b654-4373-b73c-4d4a45e29b46","target":"1cea6d1c-2351-4015-b1d3-60950fb858f4","weight":1,"viz":{},"attributes":{"attr_count":3},"size":1},{"id":"e64","type":"directed","label":"","source":"c8983b72-3f60-4f05-8bdc-20abf3308f0f","target":"e6e26f1f-bad1-4540-b426-ca95f337f069","weight":1,"viz":{},"attributes":{"attr_count":3},"size":1},{"id":"e65","type":"directed","label":"","source":"c8983b72-3f60-4f05-8bdc-20abf3308f0f","target":"51277a5b-abca-424b-bde8-b8c36027010e","weight":1,"viz":{},"attributes":{"attr_count":536},"size":1},{"id":"e66","type":"directed","label":"","source":"c8983b72-3f60-4f05-8bdc-20abf3308f0f","target":"8013c65b-d8c6-4a60-9312-54f055ac9ed0","weight":1,"viz":{},"attributes":{"attr_count":9},"size":1},{"id":"e67","type":"directed","label":"","source":"c8983b72-3f60-4f05-8bdc-20abf3308f0f","target":"cea02a85-5805-49a7-90c9-df935656974a","weight":1,"viz":{},"attributes":{"attr_count":2},"size":1}]},"snapshots":{"aa1633a4-d0d8-4145-b35e-a1ac1e29b197":{"view":{"camera":{"x":-26.36068137216816,"y":-18.632092931385674,"ratio":0.8888888888888888,"angle":0}},"filters":[{"category":"expression_domain_id","values":[]}],"id":"aa1633a4-d0d8-4145-b35e-a1ac1e29b197"}}}
